mapequation/__init__.py
mapequation/codelength.py
mapequation/grassberger.py
mapequation/read_file.py
mapequation-0.3.0.dist-info/LICENSE
mapequation-0.3.0.dist-info/METADATA
mapequation-0.3.0.dist-info/WHEEL
mapequation-0.3.0.dist-info/top_level.txt
mapequation-0.3.0.dist-info/RECORD
